{
  "uid": "jam-service",
  "title": "JAMswap service",
  "timezone": "browser",
  "refresh": "5s",
  "time": {
    "from": "now-30m",
    "to": "now"
  },
  "editable": true,
  "panels": [
    {
      "type": "stat",
      "title": "Settle success (15m)",
      "id": 45,
      "gridPos": {
        "x": 0,
        "y": 0,
        "w": 4,
        "h": 4
      },
      "datasource": {
        "type": "prometheus",
        "uid": "prometheus"
      },
      "targets": [
        {
          "expr": "sum(increase(jamswap_settled_total[15m])) / sum(increase(jamswap_submits_total{op=~\"register|deposit|withdraw|cancel\"}[15m]))",
          "instant": true,
          "refId": "A"
        }
      ],
      "fieldConfig": {
        "defaults": {
          "decimals": 0,
          "color": {
            "mode": "thresholds"
          },
          "thresholds": {
            "mode": "absolute",
            "steps": [
              {
                "color": "red",
                "value": null
              },
              {
                "color": "orange",
                "value": 0.5
              },
              {
                "color": "green",
                "value": 0.99
              }
            ]
          },
          "unit": "percentunit"
        },
        "overrides": []
      },
      "options": {
        "graphMode": "none",
        "colorMode": "value",
        "textMode": "value"
      }
    },
    {
      "type": "stat",
      "title": "Settle p95 (15m)",
      "id": 46,
      "gridPos": {
        "x": 4,
        "y": 0,
        "w": 4,
        "h": 4
      },
      "datasource": {
        "type": "prometheus",
        "uid": "prometheus"
      },
      "targets": [
        {
          "expr": "histogram_quantile(0.95, sum by (le) (rate(jamswap_settle_latency_seconds_bucket[15m])))",
          "instant": true,
          "refId": "A"
        }
      ],
      "fieldConfig": {
        "defaults": {
          "decimals": 0,
          "color": {
            "mode": "thresholds"
          },
          "thresholds": {
            "mode": "absolute",
            "steps": [
              {
                "color": "green",
                "value": null
              },
              {
                "color": "orange",
                "value": 60
              },
              {
                "color": "red",
                "value": 120
              }
            ]
          },
          "unit": "s"
        },
        "overrides": []
      },
      "options": {
        "graphMode": "none",
        "colorMode": "value",
        "textMode": "value"
      }
    },
    {
      "type": "stat",
      "title": "Ops in flight",
      "id": 47,
      "gridPos": {
        "x": 8,
        "y": 0,
        "w": 4,
        "h": 4
      },
      "datasource": {
        "type": "prometheus",
        "uid": "prometheus"
      },
      "targets": [
        {
          "expr": "clamp_min(sum(jamswap_submits_total{op=~\"register|deposit|withdraw|cancel\"}) - sum(jamswap_settled_total) - sum(jamswap_settle_timeouts_total), 0)",
          "instant": true,
          "refId": "A"
        }
      ],
      "fieldConfig": {
        "defaults": {
          "decimals": 0,
          "color": {
            "mode": "thresholds"
          },
          "thresholds": {
            "mode": "absolute",
            "steps": [
              {
                "color": "green",
                "value": null
              },
              {
                "color": "orange",
                "value": 5
              },
              {
                "color": "red",
                "value": 20
              }
            ]
          }
        },
        "overrides": []
      },
      "options": {
        "graphMode": "none",
        "colorMode": "value",
        "textMode": "value"
      }
    },
    {
      "type": "stat",
      "title": "Settle timeouts (1h)",
      "id": 48,
      "gridPos": {
        "x": 12,
        "y": 0,
        "w": 4,
        "h": 4
      },
      "datasource": {
        "type": "prometheus",
        "uid": "prometheus"
      },
      "targets": [
        {
          "expr": "sum(increase(jamswap_settle_timeouts_total[1h])) or vector(0)",
          "instant": true,
          "refId": "A"
        }
      ],
      "fieldConfig": {
        "defaults": {
          "decimals": 0,
          "color": {
            "mode": "thresholds"
          },
          "thresholds": {
            "mode": "absolute",
            "steps": [
              {
                "color": "green",
                "value": null
              },
              {
                "color": "red",
                "value": 1
              }
            ]
          }
        },
        "overrides": []
      },
      "options": {
        "graphMode": "none",
        "colorMode": "value",
        "textMode": "value"
      }
    },
    {
      "type": "stat",
      "title": "Canary last pass age",
      "id": 49,
      "gridPos": {
        "x": 16,
        "y": 0,
        "w": 4,
        "h": 4
      },
      "datasource": {
        "type": "prometheus",
        "uid": "prometheus"
      },
      "targets": [
        {
          "expr": "jamswap_canary_last_pass_age_seconds",
          "instant": true,
          "refId": "A"
        }
      ],
      "fieldConfig": {
        "defaults": {
          "decimals": 0,
          "color": {
            "mode": "thresholds"
          },
          "thresholds": {
            "mode": "absolute",
            "steps": [
              {
                "color": "green",
                "value": null
              },
              {
                "color": "orange",
                "value": 600
              },
              {
                "color": "red",
                "value": 900
              }
            ]
          },
          "unit": "s"
        },
        "overrides": []
      },
      "options": {
        "graphMode": "none",
        "colorMode": "value",
        "textMode": "value"
      }
    },
    {
      "type": "stat",
      "title": "Accounts on-chain",
      "id": 50,
      "gridPos": {
        "x": 20,
        "y": 0,
        "w": 4,
        "h": 4
      },
      "datasource": {
        "type": "prometheus",
        "uid": "prometheus"
      },
      "targets": [
        {
          "expr": "jamswap_accounts_registered",
          "instant": true,
          "refId": "A"
        }
      ],
      "fieldConfig": {
        "defaults": {
          "decimals": 0,
          "color": {
            "mode": "fixed",
            "fixedColor": "text"
          }
        },
        "overrides": []
      },
      "options": {
        "graphMode": "none",
        "colorMode": "value",
        "textMode": "value"
      }
    },
    {
      "type": "timeseries",
      "title": "Order funnel (per 5m) \u2014 dex submits once; node-side stages count all 3 lm nodes",
      "id": 51,
      "gridPos": {
        "x": 0,
        "y": 4,
        "w": 12,
        "h": 8
      },
      "datasource": {
        "type": "prometheus",
        "uid": "prometheus"
      },
      "targets": [
        {
          "expr": "sum(increase(jamswap_submits_total{op=~\"register|deposit|withdraw|cancel\"}[5m]))",
          "legendFormat": "submitted (dex)",
          "refId": "A"
        },
        {
          "expr": "sum(increase(lasair_ce133_queued_total[5m]))",
          "legendFormat": "queued (3x)",
          "refId": "B"
        },
        {
          "expr": "sum(increase(lasair_ce133_guaranteed_total[5m]))",
          "legendFormat": "guaranteed",
          "refId": "C"
        },
        {
          "expr": "sum(increase(lasair_ce133_accumulated_total[5m]))",
          "legendFormat": "accumulated",
          "refId": "D"
        },
        {
          "expr": "sum(increase(jamswap_settled_total[5m]))",
          "legendFormat": "settled (dex)",
          "refId": "E"
        }
      ],
      "fieldConfig": {
        "defaults": {
          "custom": {
            "lineWidth": 2,
            "fillOpacity": 0,
            "pointSize": 4,
            "showPoints": "never"
          },
          "color": {
            "mode": "palette-classic"
          },
          "min": 0
        },
        "overrides": [
          {
            "matcher": {
              "id": "byName",
              "options": "submitted (dex)"
            },
            "properties": [
              {
                "id": "color",
                "value": {
                  "mode": "fixed",
                  "fixedColor": "#c98500"
                }
              }
            ]
          },
          {
            "matcher": {
              "id": "byName",
              "options": "queued (3x)"
            },
            "properties": [
              {
                "id": "color",
                "value": {
                  "mode": "fixed",
                  "fixedColor": "#9085e9"
                }
              }
            ]
          },
          {
            "matcher": {
              "id": "byName",
              "options": "guaranteed"
            },
            "properties": [
              {
                "id": "color",
                "value": {
                  "mode": "fixed",
                  "fixedColor": "#3987e5"
                }
              }
            ]
          },
          {
            "matcher": {
              "id": "byName",
              "options": "accumulated"
            },
            "properties": [
              {
                "id": "color",
                "value": {
                  "mode": "fixed",
                  "fixedColor": "#199e70"
                }
              }
            ]
          },
          {
            "matcher": {
              "id": "byName",
              "options": "settled (dex)"
            },
            "properties": [
              {
                "id": "color",
                "value": {
                  "mode": "fixed",
                  "fixedColor": "#008300"
                }
              }
            ]
          }
        ]
      },
      "options": {
        "legend": {
          "displayMode": "list",
          "placement": "bottom",
          "showLegend": true
        },
        "tooltip": {
          "mode": "multi",
          "sort": "desc"
        }
      }
    },
    {
      "type": "timeseries",
      "title": "Settle latency \u2014 percentiles (10m) + canary e2e",
      "id": 52,
      "gridPos": {
        "x": 12,
        "y": 4,
        "w": 12,
        "h": 8
      },
      "datasource": {
        "type": "prometheus",
        "uid": "prometheus"
      },
      "targets": [
        {
          "expr": "histogram_quantile(0.50, sum by (le) (rate(jamswap_settle_latency_seconds_bucket[10m])))",
          "legendFormat": "p50",
          "refId": "A"
        },
        {
          "expr": "histogram_quantile(0.95, sum by (le) (rate(jamswap_settle_latency_seconds_bucket[10m])))",
          "legendFormat": "p95",
          "refId": "B"
        },
        {
          "expr": "rate(jamswap_canary_duration_seconds_sum[30m]) / rate(jamswap_canary_duration_seconds_count[30m])",
          "legendFormat": "canary full cycle (avg 30m)",
          "refId": "C"
        }
      ],
      "fieldConfig": {
        "defaults": {
          "custom": {
            "lineWidth": 2,
            "fillOpacity": 0,
            "pointSize": 4,
            "showPoints": "never"
          },
          "color": {
            "mode": "palette-classic"
          },
          "unit": "s",
          "min": 0
        },
        "overrides": [
          {
            "matcher": {
              "id": "byName",
              "options": "p50"
            },
            "properties": [
              {
                "id": "color",
                "value": {
                  "mode": "fixed",
                  "fixedColor": "#199e70"
                }
              }
            ]
          },
          {
            "matcher": {
              "id": "byName",
              "options": "p95"
            },
            "properties": [
              {
                "id": "color",
                "value": {
                  "mode": "fixed",
                  "fixedColor": "#c98500"
                }
              }
            ]
          },
          {
            "matcher": {
              "id": "byName",
              "options": "canary full cycle (avg 30m)"
            },
            "properties": [
              {
                "id": "color",
                "value": {
                  "mode": "fixed",
                  "fixedColor": "#9085e9"
                }
              }
            ]
          }
        ]
      },
      "options": {
        "legend": {
          "displayMode": "list",
          "placement": "bottom",
          "showLegend": true
        },
        "tooltip": {
          "mode": "multi",
          "sort": "desc"
        }
      }
    },
    {
      "type": "timeseries",
      "title": "Guarantee outcomes, all lm nodes (per 5m) \u2014 requeued = lost fork race or timeout",
      "id": 53,
      "gridPos": {
        "x": 0,
        "y": 12,
        "w": 8,
        "h": 8
      },
      "datasource": {
        "type": "prometheus",
        "uid": "prometheus"
      },
      "targets": [
        {
          "expr": "sum(increase(lasair_ce133_guaranteed_total[5m]))",
          "legendFormat": "guaranteed",
          "refId": "A"
        },
        {
          "expr": "sum(increase(lasair_ce133_requeued_total[5m]))",
          "legendFormat": "requeued",
          "refId": "B"
        },
        {
          "expr": "sum(increase(lasair_ce133_dropped_total[5m]))",
          "legendFormat": "dropped (duplicate)",
          "refId": "C"
        }
      ],
      "fieldConfig": {
        "defaults": {
          "custom": {
            "lineWidth": 2,
            "fillOpacity": 0,
            "pointSize": 4,
            "showPoints": "never"
          },
          "color": {
            "mode": "palette-classic"
          },
          "min": 0
        },
        "overrides": [
          {
            "matcher": {
              "id": "byName",
              "options": "guaranteed"
            },
            "properties": [
              {
                "id": "color",
                "value": {
                  "mode": "fixed",
                  "fixedColor": "#199e70"
                }
              }
            ]
          },
          {
            "matcher": {
              "id": "byName",
              "options": "requeued"
            },
            "properties": [
              {
                "id": "color",
                "value": {
                  "mode": "fixed",
                  "fixedColor": "#c98500"
                }
              }
            ]
          },
          {
            "matcher": {
              "id": "byName",
              "options": "dropped (duplicate)"
            },
            "properties": [
              {
                "id": "color",
                "value": {
                  "mode": "fixed",
                  "fixedColor": "#e66767"
                }
              }
            ]
          }
        ]
      },
      "options": {
        "legend": {
          "displayMode": "list",
          "placement": "bottom",
          "showLegend": true
        },
        "tooltip": {
          "mode": "multi",
          "sort": "desc"
        }
      }
    },
    {
      "type": "timeseries",
      "title": "CE-133 queue depth per lm node \u2014 sustained growth = settlement can't keep up",
      "id": 54,
      "gridPos": {
        "x": 8,
        "y": 12,
        "w": 8,
        "h": 8
      },
      "datasource": {
        "type": "prometheus",
        "uid": "prometheus"
      },
      "targets": [
        {
          "expr": "lasair_ce133_queue_depth",
          "legendFormat": "{{node}}",
          "refId": "A"
        }
      ],
      "fieldConfig": {
        "defaults": {
          "custom": {
            "lineWidth": 2,
            "fillOpacity": 0,
            "pointSize": 4,
            "showPoints": "never"
          },
          "color": {
            "mode": "palette-classic"
          },
          "min": 0
        },
        "overrides": [
          {
            "matcher": {
              "id": "byName",
              "options": "lm3"
            },
            "properties": [
              {
                "id": "color",
                "value": {
                  "mode": "fixed",
                  "fixedColor": "#008300"
                }
              }
            ]
          },
          {
            "matcher": {
              "id": "byName",
              "options": "lm4"
            },
            "properties": [
              {
                "id": "color",
                "value": {
                  "mode": "fixed",
                  "fixedColor": "#9085e9"
                }
              }
            ]
          },
          {
            "matcher": {
              "id": "byName",
              "options": "lm5"
            },
            "properties": [
              {
                "id": "color",
                "value": {
                  "mode": "fixed",
                  "fixedColor": "#e66767"
                }
              }
            ]
          }
        ]
      },
      "options": {
        "legend": {
          "displayMode": "list",
          "placement": "bottom",
          "showLegend": true
        },
        "tooltip": {
          "mode": "multi",
          "sort": "desc"
        }
      }
    },
    {
      "type": "timeseries",
      "title": "Availability work (per 5m): cores assured / items accumulated",
      "id": 55,
      "gridPos": {
        "x": 16,
        "y": 12,
        "w": 8,
        "h": 8
      },
      "datasource": {
        "type": "prometheus",
        "uid": "prometheus"
      },
      "targets": [
        {
          "expr": "sum(increase(lasair_ce133_assured_cores_total[5m]))",
          "legendFormat": "cores assured",
          "refId": "A"
        },
        {
          "expr": "sum(increase(lasair_ce133_accumulated_total[5m]))",
          "legendFormat": "accumulated",
          "refId": "B"
        }
      ],
      "fieldConfig": {
        "defaults": {
          "custom": {
            "lineWidth": 2,
            "fillOpacity": 0,
            "pointSize": 4,
            "showPoints": "never"
          },
          "color": {
            "mode": "palette-classic"
          },
          "min": 0
        },
        "overrides": [
          {
            "matcher": {
              "id": "byName",
              "options": "cores assured"
            },
            "properties": [
              {
                "id": "color",
                "value": {
                  "mode": "fixed",
                  "fixedColor": "#9085e9"
                }
              }
            ]
          },
          {
            "matcher": {
              "id": "byName",
              "options": "accumulated"
            },
            "properties": [
              {
                "id": "color",
                "value": {
                  "mode": "fixed",
                  "fixedColor": "#199e70"
                }
              }
            ]
          }
        ]
      },
      "options": {
        "legend": {
          "displayMode": "list",
          "placement": "bottom",
          "showLegend": true
        },
        "tooltip": {
          "mode": "multi",
          "sort": "desc"
        }
      }
    },
    {
      "type": "timeseries",
      "title": "Settle latency by op (avg, 10m)",
      "id": 56,
      "gridPos": {
        "x": 0,
        "y": 20,
        "w": 12,
        "h": 8
      },
      "datasource": {
        "type": "prometheus",
        "uid": "prometheus"
      },
      "targets": [
        {
          "expr": "sum by (op) (rate(jamswap_settle_latency_seconds_sum[10m])) / sum by (op) (rate(jamswap_settle_latency_seconds_count[10m]))",
          "legendFormat": "{{op}}",
          "refId": "A"
        }
      ],
      "fieldConfig": {
        "defaults": {
          "custom": {
            "lineWidth": 2,
            "fillOpacity": 0,
            "pointSize": 4,
            "showPoints": "never"
          },
          "color": {
            "mode": "palette-classic"
          },
          "unit": "s",
          "min": 0
        },
        "overrides": [
          {
            "matcher": {
              "id": "byName",
              "options": "register"
            },
            "properties": [
              {
                "id": "color",
                "value": {
                  "mode": "fixed",
                  "fixedColor": "#3987e5"
                }
              }
            ]
          },
          {
            "matcher": {
              "id": "byName",
              "options": "deposit"
            },
            "properties": [
              {
                "id": "color",
                "value": {
                  "mode": "fixed",
                  "fixedColor": "#199e70"
                }
              }
            ]
          },
          {
            "matcher": {
              "id": "byName",
              "options": "withdraw"
            },
            "properties": [
              {
                "id": "color",
                "value": {
                  "mode": "fixed",
                  "fixedColor": "#c98500"
                }
              }
            ]
          },
          {
            "matcher": {
              "id": "byName",
              "options": "cancel"
            },
            "properties": [
              {
                "id": "color",
                "value": {
                  "mode": "fixed",
                  "fixedColor": "#9085e9"
                }
              }
            ]
          }
        ]
      },
      "options": {
        "legend": {
          "displayMode": "list",
          "placement": "bottom",
          "showLegend": true
        },
        "tooltip": {
          "mode": "multi",
          "sort": "desc"
        }
      }
    },
    {
      "type": "timeseries",
      "title": "Service state: accounts + resting orders",
      "id": 57,
      "gridPos": {
        "x": 12,
        "y": 20,
        "w": 6,
        "h": 8
      },
      "datasource": {
        "type": "prometheus",
        "uid": "prometheus"
      },
      "targets": [
        {
          "expr": "jamswap_accounts_registered",
          "legendFormat": "accounts",
          "refId": "A"
        },
        {
          "expr": "jamswap_resting_orders",
          "legendFormat": "resting orders",
          "refId": "B"
        }
      ],
      "fieldConfig": {
        "defaults": {
          "custom": {
            "lineWidth": 2,
            "fillOpacity": 0,
            "pointSize": 4,
            "showPoints": "never"
          },
          "color": {
            "mode": "palette-classic"
          },
          "min": 0
        },
        "overrides": [
          {
            "matcher": {
              "id": "byName",
              "options": "accounts"
            },
            "properties": [
              {
                "id": "color",
                "value": {
                  "mode": "fixed",
                  "fixedColor": "#3987e5"
                }
              }
            ]
          },
          {
            "matcher": {
              "id": "byName",
              "options": "resting orders"
            },
            "properties": [
              {
                "id": "color",
                "value": {
                  "mode": "fixed",
                  "fixedColor": "#c98500"
                }
              }
            ]
          }
        ]
      },
      "options": {
        "legend": {
          "displayMode": "list",
          "placement": "bottom",
          "showLegend": true
        },
        "tooltip": {
          "mode": "multi",
          "sort": "desc"
        }
      }
    },
    {
      "type": "timeseries",
      "title": "Treasury JAMKB: held vs reserve target (atomic)",
      "id": 58,
      "gridPos": {
        "x": 18,
        "y": 20,
        "w": 6,
        "h": 8
      },
      "datasource": {
        "type": "prometheus",
        "uid": "prometheus"
      },
      "targets": [
        {
          "expr": "jamswap_treasury_jamkb_atomic",
          "legendFormat": "held",
          "refId": "A"
        },
        {
          "expr": "jamswap_treasury_reserve_target_atomic",
          "legendFormat": "target",
          "refId": "B"
        }
      ],
      "fieldConfig": {
        "defaults": {
          "custom": {
            "lineWidth": 2,
            "fillOpacity": 0,
            "pointSize": 4,
            "showPoints": "never"
          },
          "color": {
            "mode": "palette-classic"
          },
          "min": 0
        },
        "overrides": [
          {
            "matcher": {
              "id": "byName",
              "options": "held"
            },
            "properties": [
              {
                "id": "color",
                "value": {
                  "mode": "fixed",
                  "fixedColor": "#199e70"
                }
              }
            ]
          },
          {
            "matcher": {
              "id": "byName",
              "options": "target"
            },
            "properties": [
              {
                "id": "color",
                "value": {
                  "mode": "fixed",
                  "fixedColor": "#e66767"
                }
              }
            ]
          }
        ]
      },
      "options": {
        "legend": {
          "displayMode": "list",
          "placement": "bottom",
          "showLegend": true
        },
        "tooltip": {
          "mode": "multi",
          "sort": "desc"
        }
      }
    },
    {
      "type": "timeseries",
      "title": "API requests by route (per 5m)",
      "id": 59,
      "gridPos": {
        "x": 0,
        "y": 28,
        "w": 8,
        "h": 8
      },
      "datasource": {
        "type": "prometheus",
        "uid": "prometheus"
      },
      "targets": [
        {
          "expr": "sum by (route) (increase(jamswap_api_requests_total[5m]))",
          "legendFormat": "{{route}}",
          "refId": "A"
        }
      ],
      "fieldConfig": {
        "defaults": {
          "custom": {
            "lineWidth": 2,
            "fillOpacity": 0,
            "pointSize": 4,
            "showPoints": "never"
          },
          "color": {
            "mode": "palette-classic"
          },
          "min": 0
        },
        "overrides": []
      },
      "options": {
        "legend": {
          "displayMode": "list",
          "placement": "bottom",
          "showLegend": true
        },
        "tooltip": {
          "mode": "multi",
          "sort": "desc"
        }
      }
    },
    {
      "type": "timeseries",
      "title": "Errors: API handlers + builder per-target submit failures (per 5m)",
      "id": 60,
      "gridPos": {
        "x": 8,
        "y": 28,
        "w": 8,
        "h": 8
      },
      "datasource": {
        "type": "prometheus",
        "uid": "prometheus"
      },
      "targets": [
        {
          "expr": "sum by (route) (increase(jamswap_api_errors_total[5m]))",
          "legendFormat": "api {{route}}",
          "refId": "A"
        },
        {
          "expr": "sum by (target) (increase(builder_submit_failures_total[5m]))",
          "legendFormat": "builder -> {{target}}",
          "refId": "B"
        }
      ],
      "fieldConfig": {
        "defaults": {
          "custom": {
            "lineWidth": 2,
            "fillOpacity": 0,
            "pointSize": 4,
            "showPoints": "never"
          },
          "color": {
            "mode": "palette-classic"
          },
          "min": 0
        },
        "overrides": []
      },
      "options": {
        "legend": {
          "displayMode": "list",
          "placement": "bottom",
          "showLegend": true
        },
        "tooltip": {
          "mode": "multi",
          "sort": "desc"
        }
      }
    },
    {
      "type": "timeseries",
      "title": "Canary cycles (per 30m)",
      "id": 61,
      "gridPos": {
        "x": 16,
        "y": 28,
        "w": 8,
        "h": 8
      },
      "datasource": {
        "type": "prometheus",
        "uid": "prometheus"
      },
      "targets": [
        {
          "expr": "sum(increase(jamswap_canary_pass_total[30m]))",
          "legendFormat": "pass",
          "refId": "A"
        },
        {
          "expr": "sum by (stage) (increase(jamswap_canary_fail_total[30m]))",
          "legendFormat": "fail: {{stage}}",
          "refId": "B"
        }
      ],
      "fieldConfig": {
        "defaults": {
          "custom": {
            "lineWidth": 2,
            "fillOpacity": 0,
            "pointSize": 4,
            "showPoints": "never"
          },
          "color": {
            "mode": "palette-classic"
          },
          "min": 0
        },
        "overrides": [
          {
            "matcher": {
              "id": "byName",
              "options": "pass"
            },
            "properties": [
              {
                "id": "color",
                "value": {
                  "mode": "fixed",
                  "fixedColor": "#199e70"
                }
              }
            ]
          }
        ]
      },
      "options": {
        "legend": {
          "displayMode": "list",
          "placement": "bottom",
          "showLegend": true
        },
        "tooltip": {
          "mode": "multi",
          "sort": "desc"
        }
      }
    }
  ],
  "schemaVersion": 39,
  "version": 1,
  "links": [
    {
      "title": "JAM mixed network",
      "type": "link",
      "url": "/d/jam-mixed",
      "targetBlank": false
    },
    {
      "title": "JAM node (lasair)",
      "type": "link",
      "url": "/d/jam-node",
      "targetBlank": false
    }
  ]
}